argos/__init__.py
argos/argos_socket.py
argos/commands.py
argos/exceptions.py
argos/responses.py
argos/sdk.py
ArgosSDK-0.5.2.dist-info/METADATA
ArgosSDK-0.5.2.dist-info/WHEEL
ArgosSDK-0.5.2.dist-info/top_level.txt
ArgosSDK-0.5.2.dist-info/RECORD
