Metadata-Version: 2.1
Name: ArgosSDK
Version: 0.5.2
Summary: A SDK to handle Henry Argos Fingerprint/Card readers
Home-page: https://gitlab.com/engenharia-ufjf/biometria/argos-sdk
Author: Vinicius Schettino
Author-email: vinicius.schettino@ice.ufjf.br
License: MIT
Platform: UNKNOWN
Classifier: Programming Language :: Python :: 3
Classifier: License :: OSI Approved :: MIT License
Classifier: Operating System :: OS Independent
Requires-Python: >=3.6
Requires-Dist: daiquiri
Requires-Dist: parse
